mainframe_orchestra/__init__.py
mainframe_orchestra/adapters/__init__.py
mainframe_orchestra/adapters/mcp_adapter.py
mainframe_orchestra/agent.py
mainframe_orchestra/config.py
mainframe_orchestra/llm.py
mainframe_orchestra/orchestration.py
mainframe_orchestra/task.py
mainframe_orchestra/tools/__init__.py
mainframe_orchestra/tools/amadeus_tools.py
mainframe_orchestra/tools/audio_tools.py
mainframe_orchestra/tools/calculator_tools.py
mainframe_orchestra/tools/embedding_tools.py
mainframe_orchestra/tools/faiss_tools.py
mainframe_orchestra/tools/file_tools.py
mainframe_orchestra/tools/fred_tools.py
mainframe_orchestra/tools/github_tools.py
mainframe_orchestra/tools/langchain_tools.py
mainframe_orchestra/tools/linear_tools.py
mainframe_orchestra/tools/matplotlib_tools.py
mainframe_orchestra/tools/pinecone_tools.py
mainframe_orchestra/tools/stripe_tools.py
mainframe_orchestra/tools/text_splitters.py
mainframe_orchestra/tools/web_tools.py
mainframe_orchestra/tools/wikipedia_tools.py
mainframe_orchestra/tools/yahoo_finance_tools.py
mainframe_orchestra/utils/__init__.py
mainframe_orchestra/utils/braintrust_utils.py
mainframe_orchestra/utils/logging_config.py
mainframe_orchestra/utils/parse_json_response.py
mainframe_orchestra-0.0.34.dist-info/LICENSE.txt
mainframe_orchestra-0.0.34.dist-info/METADATA
mainframe_orchestra-0.0.34.dist-info/WHEEL
mainframe_orchestra-0.0.34.dist-info/RECORD
