Metadata-Version: 2.3
Name: mainframe-orchestra
Version: 0.0.34
Summary: Mainframe-Orchestra is a lightweight, open-source agentic framework for building LLM based pipelines and self-orchestrating multi-agent teams
License: Apache 2.0
Author: Mainframe Computer Inc.
Author-email: hi@mainfra.me
Requires-Python: >=3.10,<4.0
Classifier: Development Status :: 4 - Beta
Classifier: Intended Audience :: Developers
Classifier: License :: OSI Approved :: Apache Software License
Classifier: License :: Other/Proprietary License
Classifier: Operating System :: OS Independent
Classifier: Programming Language :: Python :: 3
Classifier: Programming Language :: Python :: 3.10
Classifier: Programming Language :: Python :: 3.11
Classifier: Programming Language :: Python :: 3.12
Classifier: Programming Language :: Python :: 3.13
Provides-Extra: audio-tools
Provides-Extra: fred-tools
Provides-Extra: langchain-tools
Provides-Extra: matplotlib-tools
Provides-Extra: stripe-tools
Provides-Extra: yahoo-finance-tools
Requires-Dist: PyYAML
Requires-Dist: anthropic
Requires-Dist: beautifulsoup4
Requires-Dist: braintrust
Requires-Dist: cohere
Requires-Dist: elevenlabs ; extra == "audio-tools"
Requires-Dist: faiss-cpu
Requires-Dist: fake-useragent
Requires-Dist: fastmcp
Requires-Dist: google-generativeai
Requires-Dist: groq
Requires-Dist: halo
Requires-Dist: huggingface-hub
Requires-Dist: igraph
Requires-Dist: langchain-community ; extra == "langchain-tools"
Requires-Dist: langchain-core ; extra == "langchain-tools"
Requires-Dist: langchain-openai ; extra == "langchain-tools"
Requires-Dist: leidenalg
Requires-Dist: lxml
Requires-Dist: matplotlib ; extra == "matplotlib-tools"
Requires-Dist: mcp
Requires-Dist: numpy
Requires-Dist: ollama
Requires-Dist: openai (>=1.0)
Requires-Dist: pinecone
Requires-Dist: pydantic (>=2.0)
Requires-Dist: python-dotenv
Requires-Dist: requests
Requires-Dist: sentence_splitter
Requires-Dist: stripe-agent-toolkit ; extra == "stripe-tools"
Requires-Dist: tqdm
Requires-Dist: tzdata (>=2024.2,<2025.0)
Requires-Dist: yahoofinance ; extra == "yahoo-finance-tools"
Requires-Dist: yfinance ; extra == "yahoo-finance-tools"
Project-URL: Bug Tracker, https://github.com/mainframecomputer/orchestra/issues
Project-URL: Documentation, https://orchestra.org
Project-URL: Homepage, https://github.com/mainframecomputer/orchestra/
